{ "height":16,
 "layers":[
        {
         "data":[1, 1, 1, 5, 5, 5, 4, 1, 1, 1, 3, 3, 3, 2, 1, 1],
         "height":16,
         "name":"RoadLayer",
         "opacity":1,
         "type":"tilelayer",
         "visible":true,
         "width":1,
         "x":0,
         "y":0
        }, 
        {
         "data":[6, 6, 6, 7, 7, 7, 6, 6, 6, 6, 6, 6, 6, 6, 6, 6],
         "height":16,
         "name":"UnderSeparatorLayer",
         "opacity":1,
         "type":"tilelayer",
         "visible":true,
         "width":1,
         "x":0,
         "y":0
        }, 
        {
         "draworder":"topdown",
         "height":16,
         "name":"CollisionsLayer",
         "objects":[
                {
                 "height":0,
                 "id":2,
                 "name":"",
                 "polyline":[
                        {
                         "x":0,
                         "y":0
                        }, 
                        {
                         "x":-3.98098633392732,
                         "y":-705.109922756981
                        }, 
                        {
                         "x":82.7391562685682,
                         "y":-713.042186571598
                        }, 
                        {
                         "x":78.7581699346409,
                         "y":-1418.15210932858
                        }, 
                        {
                         "x":-0.47534165181202,
                         "y":-1423.76708259061
                        }, 
                        {
                         "x":-4.50623885917986,
                         "y":-3771.2513368984
                        }],
                 "properties":
                    {

                    },
                 "rotation":0,
                 "type":"",
                 "visible":true,
                 "width":0,
                 "x":-0.121212121212299,
                 "y":3775.87878787879
                }, 
                {
                 "height":0,
                 "id":4,
                 "name":"",
                 "polyline":[
                        {
                         "x":0,
                         "y":0
                        }, 
                        {
                         "x":12.0000000000001,
                         "y":-2348
                        }, 
                        {
                         "x":-73.6470588235293,
                         "y":-2350.35294117647
                        }, 
                        {
                         "x":-75.6470588235293,
                         "y":-3060.35294117647
                        }, 
                        {
                         "x":8.31372549019613,
                         "y":-3064.3137254902
                        }, 
                        {
                         "x":7.3725490196079,
                         "y":-3759.37254901961
                        }],
                 "properties":
                    {

                    },
                 "rotation":0,
                 "type":"",
                 "visible":true,
                 "width":0,
                 "x":223.686274509804,
                 "y":3768.3137254902
                }],
         "opacity":1,
         "type":"objectgroup",
         "visible":true,
         "width":1,
         "x":0,
         "y":0
        }],
 "nextobjectid":5,
 "orientation":"isometric",
 "properties":
    {

    },
 "renderorder":"right-down",
 "tileheight":236,
 "tilesets":[
        {
         "firstgid":1,
         "image":"..\/assets\/Tiled\/carretera1.png",
         "imageheight":236,
         "imagewidth":408,
         "margin":0,
         "name":"carretera1",
         "properties":
            {

            },
         "spacing":0,
         "tileheight":236,
         "tilewidth":408
        }, 
        {
         "firstgid":2,
         "image":"..\/assets\/Tiled\/carretera2.png",
         "imageheight":236,
         "imagewidth":408,
         "margin":0,
         "name":"carretera2",
         "properties":
            {

            },
         "spacing":0,
         "tileheight":236,
         "tilewidth":408
        }, 
        {
         "firstgid":3,
         "image":"..\/assets\/Tiled\/carretera6.png",
         "imageheight":236,
         "imagewidth":408,
         "margin":0,
         "name":"carretera6",
         "properties":
            {

            },
         "spacing":0,
         "tileheight":236,
         "tilewidth":408
        }, 
        {
         "firstgid":4,
         "image":"..\/assets\/Tiled\/carretera4.png",
         "imageheight":236,
         "imagewidth":408,
         "margin":0,
         "name":"carretera4",
         "properties":
            {

            },
         "spacing":0,
         "tileheight":236,
         "tilewidth":408
        }, 
        {
         "firstgid":5,
         "image":"..\/assets\/Tiled\/carretera7.png",
         "imageheight":236,
         "imagewidth":408,
         "margin":0,
         "name":"carretera7",
         "properties":
            {

            },
         "spacing":0,
         "tileheight":236,
         "tilewidth":408
        }, 
        {
         "firstgid":6,
         "image":"..\/assets\/Tiled\/TileQuad_RoadToPiragna_V03.png",
         "imageheight":236,
         "imagewidth":408,
         "margin":0,
         "name":"TileQuad_RoadToPiragna_V03",
         "properties":
            {

            },
         "spacing":0,
         "tileheight":236,
         "tilewidth":408
        }, 
        {
         "firstgid":7,
         "image":"..\/assets\/Tiled\/TileQuad_RoadToPiragna_V19.png",
         "imageheight":236,
         "imagewidth":408,
         "margin":0,
         "name":"TileQuad_RoadToPiragna_V19",
         "properties":
            {

            },
         "spacing":0,
         "tileheight":236,
         "tilewidth":408
        }],
 "tilewidth":408,
 "version":1,
 "width":1
}